caux_simulator/__init__.py
caux_simulator/config.default.toml
caux_simulator/nse_logging.py
caux_simulator/nse_simulator.py
caux_simulator/nse_telescope.py
caux_simulator/nse_tui.py
caux_simulator/web_console.py
caux_simulator/bus/__init__.py
caux_simulator/bus/aux_bus.py
caux_simulator/bus/mount.py
caux_simulator/bus/utils.py
caux_simulator/devices/__init__.py
caux_simulator/devices/base.py
caux_simulator/devices/generic.py
caux_simulator/devices/gps.py
caux_simulator/devices/light.py
caux_simulator/devices/motor.py
caux_simulator/devices/power.py
caux_simulator/devices/wifi.py
caux_simulator-0.2.33.dist-info/licenses/LICENSE
caux_simulator-0.2.33.dist-info/METADATA
caux_simulator-0.2.33.dist-info/WHEEL
caux_simulator-0.2.33.dist-info/entry_points.txt
caux_simulator-0.2.33.dist-info/top_level.txt
caux_simulator-0.2.33.dist-info/RECORD
