Metadata-Version: 2.4
Name: caux-simulator
Version: 0.2.33
Summary: Unified Celestron AUX Mount Simulator
Author-email: Jochym <jochym@ifj.edu.pl>
License-Expression: GPL-3.0-or-later
Project-URL: Homepage, https://github.com/jochym/caux-simulator
Project-URL: Source, https://github.com/jochym/caux-simulator
Project-URL: Tracker, https://github.com/jochym/caux-simulator/issues
Keywords: celestron,aux,indi,telescope,simulator,astronomy
Classifier: Development Status :: 4 - Beta
Classifier: Intended Audience :: Developers
Classifier: Intended Audience :: Science/Research
Classifier: Programming Language :: Python :: 3
Classifier: Programming Language :: Python :: 3.11
Classifier: Programming Language :: Python :: 3.12
Classifier: Programming Language :: Python :: 3.13
Classifier: Topic :: Scientific/Engineering :: Astronomy
Classifier: Topic :: Software Development :: Libraries :: Python Modules
Requires-Python: >=3.11
License-File: LICENSE
Requires-Dist: pyephem
Provides-Extra: tui
Requires-Dist: textual; extra == "tui"
Provides-Extra: web
Requires-Dist: fastapi; extra == "web"
Requires-Dist: uvicorn; extra == "web"
Requires-Dist: websockets; extra == "web"
Provides-Extra: dev
Requires-Dist: pytest; extra == "dev"
Requires-Dist: pytest-asyncio; extra == "dev"
Requires-Dist: ruff; extra == "dev"
Requires-Dist: mypy; extra == "dev"
Dynamic: license-file
